openlicense/__init__.py
openlicense/__main__.py
openlicense/base.py
openlicense/cli.py
openlicense-0.0.1.dist-info/LICENSE
openlicense-0.0.1.dist-info/METADATA
openlicense-0.0.1.dist-info/WHEEL
openlicense-0.0.1.dist-info/entry_points.txt
openlicense-0.0.1.dist-info/top_level.txt
openlicense-0.0.1.dist-info/RECORD
